nsf2midi/__init__.py
nsf2midi/__main__.py
nsf2midi-1.0.4.dist-info/LICENSE
nsf2midi-1.0.4.dist-info/METADATA
nsf2midi-1.0.4.dist-info/WHEEL
nsf2midi-1.0.4.dist-info/top_level.txt
nsf2midi-1.0.4.dist-info/RECORD
