Metadata-Version: 2.1
Name: nsf2midi
Version: 1.0.4
Summary: Convert NSF music to MIDI
Author: Sun Xufei
License: BSD 3-Clause License        
Project-URL: Homepage, https://github.com/realpython/reader
Keywords: feed,reader,tutorial
Classifier: License :: OSI Approved :: MIT License
License-File: LICENSE
Requires-Dist: mido (>=1.2.10)
